apify_shared/__init__.py
apify_shared/consts.py
apify_shared/models.py
apify_shared/py.typed
apify_shared/types.py
apify_shared/utils.py
apify_shared-1.4.2.dist-info/licenses/LICENSE
apify_shared-1.4.2.dist-info/METADATA
apify_shared-1.4.2.dist-info/WHEEL
apify_shared-1.4.2.dist-info/top_level.txt
apify_shared-1.4.2.dist-info/RECORD
